deepsa/__init__.py
deepsa/cli.py
deepsa/predictor.py
deepsa/trainer.py
deepsa/utils.py
deepsa/model/assets.json
deepsa/model/config.yaml
deepsa/model/data_processors.pkl
deepsa/model/df_preprocessor.pkl
deepsa/model/hparams.yaml
deepsa/model/model.ckpt
deepsa/model/hf_text/added_tokens.json
deepsa/model/hf_text/config.json
deepsa/model/hf_text/merges.txt
deepsa/model/hf_text/special_tokens_map.json
deepsa/model/hf_text/tokenizer.json
deepsa/model/hf_text/tokenizer_config.json
deepsa/model/hf_text/vocab.json
deepsa-0.1.2.dist-info/LICENSE
deepsa-0.1.2.dist-info/METADATA
deepsa-0.1.2.dist-info/WHEEL
deepsa-0.1.2.dist-info/entry_points.txt
deepsa-0.1.2.dist-info/top_level.txt
deepsa-0.1.2.dist-info/RECORD
