Metadata-Version: 2.1
Name: deepsa
Version: 0.1.2
Summary: A Deep-learning Driven Predictor of Compound Synthesis Accessibility
Home-page: https://github.com/Shihang-Wang-58/DeepSA
Author: Shihang Wang
Author-email: Shihang Wang <wangshh12022@shanghaitech.edu.cn>
Project-URL: Homepage, https://github.com/Shihang-Wang-58/DeepSA
Project-URL: Bug Tracker, https://github.com/Shihang-Wang-58/DeepSA/issues
Classifier: Programming Language :: Python :: 3
Classifier: License :: OSI Approved :: MIT License
Classifier: Operating System :: OS Independent
Requires-Python: >=3.8
License-File: LICENSE
